{
  "project_info": {
    "project_number": "1082330876834",
    "project_id": "murna-shopping",
    "storage_bucket": "murna-shopping.firebasestorage.app"
  },
  "client": [
    {
      "client_info": {
        "mobilesdk_app_id": "1:1082330876834:android:d822f9c983fd44c206c0fb",
        "android_client_info": {
          "package_name": "com.aminou_zakara.murnashopping"
        }
      },
      "oauth_client": [
        {
          "client_id": "1082330876834-gpi9ahh9s1qie8b349kdmf82nv5o4tnm.apps.googleusercontent.com",
          "client_type": 1,
          "android_info": {
            "package_name": "com.aminou_zakara.murnashopping",
            "certificate_hash": "a0e7cf67b286a69a0f5ccb75e7c765e51775d773"
          }
        },
        {
          "client_id": "1082330876834-ejjoev3pegtcp9s10ug5j0l76ok2lsk9.apps.googleusercontent.com",
          "client_type": 3
        }
      ],
      "api_key": [
        {
          "current_key": "AIzaSyDAtxj3G95kOsC1aHskCejgD_Gx4opEHeU"
        }
      ],
      "services": {
        "appinvite_service": {
          "other_platform_oauth_client": [
            {
              "client_id": "1082330876834-ejjoev3pegtcp9s10ug5j0l76ok2lsk9.apps.googleusercontent.com",
              "client_type": 3
            }
          ]
        }
      }
    }
  ],
  "configuration_version": "1"
}